DarwinexDownloader.py
__init__.py
darwinexDownloader-0.0.3.dist-info/LICENSE.txt
darwinexDownloader-0.0.3.dist-info/METADATA
darwinexDownloader-0.0.3.dist-info/WHEEL
darwinexDownloader-0.0.3.dist-info/top_level.txt
darwinexDownloader-0.0.3.dist-info/RECORD
