Metadata-Version: 2.1
Name: darwinexDownloader
Version: 0.0.3
Summary: Package to download historic data from Darwinex
Author-email: Iván García-Ferreira <ivan@garcia-ferreira.es>
Project-URL: Homepage, https://github.com/igarciaferreira/DarwinexDownloader
Project-URL: Bug Tracker, https://github.com/igarciaferreira/DarwinexDownloader/issues
Project-URL: Repository, https://github.com/igarciaferreira/DarwinexDownloader
Project-URL: Changelog, https://github.com/igarciaferreira/DarwinexDownloader/releases
Classifier: Programming Language :: Python :: 3
Classifier: License :: OSI Approved :: MIT License
Classifier: Operating System :: OS Independent
Classifier: Topic :: Office/Business :: Financial
Classifier: Topic :: Office/Business :: Financial :: Investment
Classifier: Development Status :: 3 - Alpha
Requires-Python: >=3.7
License-File: LICENSE.txt
